huaweicloudsdkcodecraft/__init__.py
huaweicloudsdkcodecraft/v5/__init__.py
huaweicloudsdkcodecraft/v5/codecraft_async_client.py
huaweicloudsdkcodecraft/v5/codecraft_client.py
huaweicloudsdkcodecraft/v5/model/__init__.py
huaweicloudsdkcodecraft/v5/model/create_competition_score_request.py
huaweicloudsdkcodecraft/v5/model/create_competition_score_response.py
huaweicloudsdkcodecraft/v5/model/create_scores_request_model.py
huaweicloudsdkcodecraft/v5/model/list_competition_works_request.py
huaweicloudsdkcodecraft/v5/model/list_competition_works_response.py
huaweicloudsdkcodecraft/v5/model/list_works_response_model.py
huaweicloudsdkcodecraft/v5/model/register_competition_info_request.py
huaweicloudsdkcodecraft/v5/model/register_competition_info_response.py
huaweicloudsdkcodecraft/v5/model/register_info_request_model.py
huaweicloudsdkcodecraft/v5/model/update_competition_score_request.py
huaweicloudsdkcodecraft/v5/model/update_competition_score_response.py
huaweicloudsdkcodecraft/v5/model/update_score_request_model.py
huaweicloudsdkcodecraft/v5/region/__init__.py
huaweicloudsdkcodecraft/v5/region/codecraft_region.py
huaweicloudsdkcodecraft-3.1.184.dist-info/METADATA
huaweicloudsdkcodecraft-3.1.184.dist-info/WHEEL
huaweicloudsdkcodecraft-3.1.184.dist-info/licenses/LICENSE
huaweicloudsdkcodecraft-3.1.184.dist-info/RECORD
